alignak_module_ws/__init__.py
alignak_module_ws/ws.py
alignak_module_ws/etc/__init__.py
alignak_module_ws/etc/alignak.d/alignak-module-ws.ini
alignak_module_ws/utils/__init__.py
alignak_module_ws/utils/helper.py
alignak_module_ws/utils/ws_server.py
alignak_module_ws-1.7.7.data/data/share/alignak/etc/alignak.d/alignak-module-ws.ini
alignak_module_ws-1.7.7.dist-info/METADATA
alignak_module_ws-1.7.7.dist-info/RECORD
alignak_module_ws-1.7.7.dist-info/WHEEL
alignak_module_ws-1.7.7.dist-info/top_level.txt
test/__init__.py
test/alignak_test.py
test/alignakbackend.py
test/host-simulator.py
test/test_module.py
test/test_module_backend.py
test/test_module_command.py
test/test_module_event.py
test/test_module_history.py
test/test_module_host.py
test/test_module_host_creation.py
test/test_module_host_get.py
test/test_module_host_livestate.py
test/test_module_hostgroup_get.py
test/test_module_no_backend.py
