Metadata-Version: 2.1
Name: alignak-module-ws
Version: 1.7.7
Summary: Alignak - Receiver module for the Web services
Home-page: https://github.com/Alignak-monitoring-contrib/alignak-modules-ws
Author: Frédéric Mohier
Author-email: frederic.mohier@alignak.net
License: GNU Affero General Public License, version 3
Keywords: alignak monitoring module web-services
Platform: UNKNOWN
Classifier: Development Status :: 5 - Production/Stable
Classifier: Environment :: Console
Classifier: Intended Audience :: Developers
Classifier: Intended Audience :: System Administrators
Classifier: License :: OSI Approved :: GNU Affero General Public License v3 or later (AGPLv3+)
Classifier: Natural Language :: English
Classifier: Programming Language :: Python
Classifier: Topic :: System :: Monitoring
Classifier: Topic :: System :: Systems Administration
Requires-Dist: alignak-backend-client
Requires-Dist: requests
Requires-Dist: CherryPy
